purpletag/__init__.py
purpletag/data.py
purpletag/purpletag.py
purpletag/purpletag_collect.py
purpletag/purpletag_parse.py
purpletag/purpletag_score.py
purpletag/purpletag_serve.py
purpletag/web/plot.html
purpletag-0.1.4.dist-info/DESCRIPTION.rst
purpletag-0.1.4.dist-info/entry_points.txt
purpletag-0.1.4.dist-info/METADATA
purpletag-0.1.4.dist-info/metadata.json
purpletag-0.1.4.dist-info/RECORD
purpletag-0.1.4.dist-info/top_level.txt
purpletag-0.1.4.dist-info/WHEEL
