Metadata-Version: 2.0
Name: purpletag
Version: 0.1.4
Summary: A tool to track hashtags used by members of the U.S. congress.
Home-page: https://github.com/casmlab/purpletag
Author: Aron Culotta
Author-email: aronwc@gmail.com
License: BSD
Keywords: purpletag
Platform: UNKNOWN
Classifier: Development Status :: 2 - Pre-Alpha
Classifier: Intended Audience :: Developers
Classifier: License :: OSI Approved :: BSD License
Classifier: Natural Language :: English
Classifier: Programming Language :: Python :: 2
Classifier: Programming Language :: Python :: 2.6
Classifier: Programming Language :: Python :: 2.7
Classifier: Programming Language :: Python :: 3
Classifier: Programming Language :: Python :: 3.3
